{
  "$schema": "https://raw.githubusercontent.com/Universal-Byte-Code/schema/refs/heads/main/.ubc.ast.json",
  "RootSentence": {
    "Nodes": [],
    "Sentences": [
      {
        "Nodes": [
          {
            "Entity": {},
            "Children": [
              {
                "Entity": {},
                "Children": null,
                "Tokens": [
                  {
                    "Source": "t_int32",
                    "Line": 2,
                    "StartColumn": 4,
                    "EndColumn": 11,
                    "Scopes": [
                      "source.ubytec",
                      "storage.type.single.ubytec"
                    ],
                    "Metadata": {
                      "guid": "01965b0f-5546-72da-a70e-5b9e79c989f4"
                    }
                  },
                  {
                    "Source": "i",
                    "Line": 2,
                    "StartColumn": 12,
                    "EndColumn": 13,
                    "Scopes": [
                      "source.ubytec",
                      "entity.name.var.explicit.ubytec"
                    ],
                    "Metadata": {
                      "guid": "01965b0f-5546-7362-b9aa-2205886116e9"
                    }
                  },
                  {
                    "Source": "0",
                    "Line": 2,
                    "StartColumn": 14,
                    "EndColumn": 15,
                    "Scopes": [
                      "source.ubytec",
                      "constant.numeric.int.ubytec"
                    ],
                    "Metadata": {
                      "guid": "01965b0f-5546-79c4-b05b-81b354a84a44"
                    }
                  }
                ],
                "Metadata": {
                  "guid": "01965b0f-5563-7c40-983f-5193c3f7fecf"
                },
                "IsHighLevel": false,
                "IsOpCode": true
              },
              {
                "Entity": {},
                "Children": null,
                "Tokens": [
                  {
                    "Source": "end",
                    "Line": 20,
                    "StartColumn": 0,
                    "EndColumn": 3,
                    "Scopes": [
                      "source.ubytec",
                      "keyword.control.flow.ubytec"
                    ],
                    "Metadata": {
                      "guid": "01965b0f-5547-713f-ba79-4a75e9d5b1f6"
                    }
                  }
                ],
                "Metadata": {
                  "guid": "01965b0f-5564-7215-8412-9326fcf16970"
                },
                "IsHighLevel": false,
                "IsOpCode": true
              }
            ],
            "Tokens": [
              {
                "Source": "block",
                "Line": 1,
                "StartColumn": 0,
                "EndColumn": 5,
                "Scopes": [
                  "source.ubytec",
                  "keyword.control.flow.ubytec"
                ],
                "Metadata": {
                  "guid": "01965b0f-5545-788c-a86d-2cd5f8a2f70e"
                }
              },
              {
                "Source": "t_void",
                "Line": 1,
                "StartColumn": 6,
                "EndColumn": 12,
                "Scopes": [
                  "source.ubytec",
                  "storage.type.single.ubytec"
                ],
                "Metadata": {
                  "guid": "01965b0f-5545-7b11-a8e1-ab4d7aaa6604"
                }
              }
            ],
            "Metadata": {
              "guid": "01965b0f-5563-74a8-b16a-7f7058986e1b",
              "depth": "",
              "initialDepth": ""
            },
            "IsHighLevel": false,
            "IsOpCode": true
          }
        ],
        "Sentences": [
          {
            "Nodes": [
              {
                "Entity": {},
                "Children": [
                  {
                    "Entity": {},
                    "Children": null,
                    "Tokens": [
                      {
                        "Source": "end",
                        "Line": 19,
                        "StartColumn": 4,
                        "EndColumn": 7,
                        "Scopes": [
                          "source.ubytec",
                          "keyword.control.flow.ubytec"
                        ],
                        "Metadata": {
                          "guid": "01965b0f-5547-7f7e-8bfb-74b7124c13d1"
                        }
                      }
                    ],
                    "Metadata": {
                      "guid": "01965b0f-5564-7bfa-8182-bf863ad3d3e7"
                    },
                    "IsHighLevel": false,
                    "IsOpCode": true
                  }
                ],
                "Tokens": [
                  {
                    "Source": "while",
                    "Line": 3,
                    "StartColumn": 4,
                    "EndColumn": 9,
                    "Scopes": [
                      "source.ubytec",
                      "keyword.control.flow.ubytec"
                    ],
                    "Metadata": {
                      "guid": "01965b0f-5546-736b-b517-f09a0e561f57"
                    }
                  },
                  {
                    "Source": "2",
                    "Line": 3,
                    "StartColumn": 10,
                    "EndColumn": 11,
                    "Scopes": [
                      "source.ubytec",
                      "constant.numeric.int.ubytec"
                    ],
                    "Metadata": {
                      "guid": "01965b0f-5546-7ed2-aa27-eba18a54c557"
                    }
                  },
                  {
                    "Source": "!=",
                    "Line": 3,
                    "StartColumn": 12,
                    "EndColumn": 14,
                    "Scopes": [
                      "source.ubytec",
                      "operator.inequality.ubytec"
                    ],
                    "Metadata": {
                      "guid": "01965b0f-5546-7792-8cbd-82859d53ccb7"
                    }
                  },
                  {
                    "Source": "10",
                    "Line": 3,
                    "StartColumn": 15,
                    "EndColumn": 17,
                    "Scopes": [
                      "source.ubytec",
                      "constant.numeric.int.ubytec"
                    ],
                    "Metadata": {
                      "guid": "01965b0f-5546-79b8-9816-ed88f5e911d9"
                    }
                  }
                ],
                "Metadata": {
                  "guid": "01965b0f-5563-71d5-a0d5-5b8d8f14f01c",
                  "depth": "  ",
                  "initialDepth": "  "
                },
                "IsHighLevel": false,
                "IsOpCode": true
              }
            ],
            "Sentences": [
              {
                "Nodes": [
                  {
                    "Entity": {},
                    "Children": [
                      {
                        "Entity": {},
                        "Children": null,
                        "Tokens": [
                          {
                            "Source": "end",
                            "Line": 10,
                            "StartColumn": 8,
                            "EndColumn": 11,
                            "Scopes": [
                              "source.ubytec",
                              "keyword.control.flow.ubytec"
                            ],
                            "Metadata": {
                              "guid": "01965b0f-5547-75f8-9f3f-f7cfe8c4b0b1"
                            }
                          }
                        ],
                        "Metadata": {
                          "guid": "01965b0f-5563-71c1-a16d-30c416fb0793"
                        },
                        "IsHighLevel": false,
                        "IsOpCode": true
                      }
                    ],
                    "Tokens": [
                      {
                        "Source": "loop",
                        "Line": 4,
                        "StartColumn": 8,
                        "EndColumn": 12,
                        "Scopes": [
                          "source.ubytec",
                          "keyword.control.flow.ubytec"
                        ],
                        "Metadata": {
                          "guid": "01965b0f-5546-70ed-940f-7d0d4ddf52e9"
                        }
                      },
                      {
                        "Source": "t_bool",
                        "Line": 4,
                        "StartColumn": 13,
                        "EndColumn": 19,
                        "Scopes": [
                          "source.ubytec",
                          "storage.type.single.ubytec"
                        ],
                        "Metadata": {
                          "guid": "01965b0f-5546-7866-885e-d962c188512c"
                        }
                      }
                    ],
                    "Metadata": {
                      "guid": "01965b0f-5563-75e2-9161-4a12f1bdd579",
                      "depth": "    ",
                      "initialDepth": "    "
                    },
                    "IsHighLevel": false,
                    "IsOpCode": true
                  }
                ],
                "Sentences": [
                  {
                    "Nodes": [
                      {
                        "Entity": {},
                        "Children": [
                          {
                            "Entity": {},
                            "Children": null,
                            "Tokens": [
                              {
                                "Source": "nop",
                                "Line": 6,
                                "StartColumn": 16,
                                "EndColumn": 19,
                                "Scopes": [
                                  "source.ubytec",
                                  "keyword.control.flow.ubytec"
                                ],
                                "Metadata": {
                                  "guid": "01965b0f-5546-7224-b239-103bc38fb8e1"
                                }
                              }
                            ],
                            "Metadata": {
                              "guid": "01965b0f-5563-7d40-8ba3-90923de362cb"
                            },
                            "IsHighLevel": false,
                            "IsOpCode": true
                          }
                        ],
                        "Tokens": [
                          {
                            "Source": "if",
                            "Line": 5,
                            "StartColumn": 12,
                            "EndColumn": 14,
                            "Scopes": [
                              "source.ubytec",
                              "keyword.control.flow.ubytec"
                            ],
                            "Metadata": {
                              "guid": "01965b0f-5546-7920-a4a0-0f91dc09d846"
                            }
                          },
                          {
                            "Source": "0",
                            "Line": 5,
                            "StartColumn": 15,
                            "EndColumn": 16,
                            "Scopes": [
                              "source.ubytec",
                              "constant.numeric.int.ubytec"
                            ],
                            "Metadata": {
                              "guid": "01965b0f-5546-7d2a-881d-279ac4e90081"
                            }
                          },
                          {
                            "Source": "==",
                            "Line": 5,
                            "StartColumn": 17,
                            "EndColumn": 19,
                            "Scopes": [
                              "source.ubytec",
                              "operator.equality.ubytec"
                            ],
                            "Metadata": {
                              "guid": "01965b0f-5546-7f8e-a5a5-992183ad3b4c"
                            }
                          },
                          {
                            "Source": "9",
                            "Line": 5,
                            "StartColumn": 20,
                            "EndColumn": 21,
                            "Scopes": [
                              "source.ubytec",
                              "constant.numeric.int.ubytec"
                            ],
                            "Metadata": {
                              "guid": "01965b0f-5546-769b-9f14-8b2df0170326"
                            }
                          }
                        ],
                        "Metadata": {
                          "guid": "01965b0f-5563-76ad-a98f-cda12abc2388",
                          "depth": "      ",
                          "initialDepth": "      "
                        },
                        "IsHighLevel": false,
                        "IsOpCode": true
                      }
                    ],
                    "Sentences": [],
                    "Metadata": {
                      "guid": "01965b0f-5563-79dd-bc54-bb8b28182110",
                      "type": "if"
                    }
                  },
                  {
                    "Nodes": [
                      {
                        "Entity": {},
                        "Children": [
                          {
                            "Entity": {},
                            "Children": null,
                            "Tokens": [
                              {
                                "Source": "nop",
                                "Line": 8,
                                "StartColumn": 16,
                                "EndColumn": 19,
                                "Scopes": [
                                  "source.ubytec",
                                  "keyword.control.flow.ubytec"
                                ],
                                "Metadata": {
                                  "guid": "01965b0f-5546-795f-9f76-3230dc276920"
                                }
                              }
                            ],
                            "Metadata": {
                              "guid": "01965b0f-5563-78ca-b41d-c94607763a9e"
                            },
                            "IsHighLevel": false,
                            "IsOpCode": true
                          },
                          {
                            "Entity": {},
                            "Children": null,
                            "Tokens": [
                              {
                                "Source": "end",
                                "Line": 9,
                                "StartColumn": 12,
                                "EndColumn": 15,
                                "Scopes": [
                                  "source.ubytec",
                                  "keyword.control.flow.ubytec"
                                ],
                                "Metadata": {
                                  "guid": "01965b0f-5546-71bb-9344-0dd2d2dc86a1"
                                }
                              }
                            ],
                            "Metadata": {
                              "guid": "01965b0f-5563-7156-a9f9-2d54bac33be4"
                            },
                            "IsHighLevel": false,
                            "IsOpCode": true
                          }
                        ],
                        "Tokens": [
                          {
                            "Source": "else",
                            "Line": 7,
                            "StartColumn": 12,
                            "EndColumn": 16,
                            "Scopes": [
                              "source.ubytec",
                              "keyword.control.flow.ubytec"
                            ],
                            "Metadata": {
                              "guid": "01965b0f-5546-73c1-9676-651691f7be47"
                            }
                          }
                        ],
                        "Metadata": {
                          "guid": "01965b0f-5563-7cae-9014-a4f59310a23b",
                          "depth": "      ",
                          "initialDepth": "        "
                        },
                        "IsHighLevel": false,
                        "IsOpCode": true
                      }
                    ],
                    "Sentences": [],
                    "Metadata": {
                      "guid": "01965b0f-5563-793d-88fb-0034e083bddd",
                      "type": "else"
                    }
                  }
                ],
                "Metadata": {
                  "guid": "01965b0f-5563-76e1-81b6-b16df9655d3c",
                  "type": "loop"
                }
              },
              {
                "Nodes": [
                  {
                    "Entity": {},
                    "Children": [
                      {
                        "Entity": {},
                        "Children": null,
                        "Tokens": [
                          {
                            "Source": "end",
                            "Line": 18,
                            "StartColumn": 8,
                            "EndColumn": 11,
                            "Scopes": [
                              "source.ubytec",
                              "keyword.control.flow.ubytec"
                            ],
                            "Metadata": {
                              "guid": "01965b0f-5547-764b-98e5-5c3dbc0dea46"
                            }
                          }
                        ],
                        "Metadata": {
                          "guid": "01965b0f-5564-7656-bd54-8fc3339eba25"
                        },
                        "IsHighLevel": false,
                        "IsOpCode": true
                      }
                    ],
                    "Tokens": [
                      {
                        "Source": "switch",
                        "Line": 11,
                        "StartColumn": 8,
                        "EndColumn": 14,
                        "Scopes": [
                          "source.ubytec",
                          "keyword.control.flow.ubytec"
                        ],
                        "Metadata": {
                          "guid": "01965b0f-5547-7522-ba1f-c3ab1dc31074"
                        }
                      }
                    ],
                    "Metadata": {
                      "guid": "01965b0f-5563-7159-a650-e5d749b55b65",
                      "depth": "    ",
                      "initialDepth": "    "
                    },
                    "IsHighLevel": false,
                    "IsOpCode": true
                  }
                ],
                "Sentences": [
                  {
                    "Nodes": [
                      {
                        "Entity": {},
                        "Children": [
                          {
                            "Entity": {},
                            "Children": null,
                            "Tokens": [
                              {
                                "Source": "nop",
                                "Line": 13,
                                "StartColumn": 16,
                                "EndColumn": 19,
                                "Scopes": [
                                  "source.ubytec",
                                  "keyword.control.flow.ubytec"
                                ],
                                "Metadata": {
                                  "guid": "01965b0f-5547-7f78-8acf-fb59ed5daa3d"
                                }
                              }
                            ],
                            "Metadata": {
                              "guid": "01965b0f-5564-7b49-9105-f9b0621d7cde"
                            },
                            "IsHighLevel": false,
                            "IsOpCode": true
                          },
                          {
                            "Entity": {},
                            "Children": null,
                            "Tokens": [
                              {
                                "Source": "break",
                                "Line": 14,
                                "StartColumn": 12,
                                "EndColumn": 17,
                                "Scopes": [
                                  "source.ubytec",
                                  "keyword.control.flow.ubytec"
                                ],
                                "Metadata": {
                                  "guid": "01965b0f-5547-7cec-b007-6081ff5d2992"
                                }
                              }
                            ],
                            "Metadata": {
                              "guid": "01965b0f-5564-7319-a128-07dc1200d1ae"
                            },
                            "IsHighLevel": false,
                            "IsOpCode": true
                          }
                        ],
                        "Tokens": [
                          {
                            "Source": "branch",
                            "Line": 12,
                            "StartColumn": 12,
                            "EndColumn": 18,
                            "Scopes": [
                              "source.ubytec",
                              "keyword.control.flow.ubytec"
                            ],
                            "Metadata": {
                              "guid": "01965b0f-5547-781d-b952-c69cb830aece"
                            }
                          },
                          {
                            "Source": "30",
                            "Line": 12,
                            "StartColumn": 19,
                            "EndColumn": 21,
                            "Scopes": [
                              "source.ubytec",
                              "constant.numeric.int.ubytec"
                            ],
                            "Metadata": {
                              "guid": "01965b0f-5547-77dc-b926-1a087c42ae8b"
                            }
                          }
                        ],
                        "Metadata": {
                          "guid": "01965b0f-5564-772e-a3e6-b5709e385367",
                          "depth": "      ",
                          "initialDepth": "      "
                        },
                        "IsHighLevel": false,
                        "IsOpCode": true
                      }
                    ],
                    "Sentences": [],
                    "Metadata": {
                      "guid": "01965b0f-5564-7b2f-b1d1-adf9e4517216",
                      "type": "branch"
                    }
                  },
                  {
                    "Nodes": [
                      {
                        "Entity": {},
                        "Children": [
                          {
                            "Entity": {},
                            "Children": null,
                            "Tokens": [
                              {
                                "Source": "trap",
                                "Line": 16,
                                "StartColumn": 16,
                                "EndColumn": 20,
                                "Scopes": [
                                  "source.ubytec",
                                  "keyword.control.flow.ubytec"
                                ],
                                "Metadata": {
                                  "guid": "01965b0f-5547-76e0-9f5c-8fdf22a7721d"
                                }
                              }
                            ],
                            "Metadata": {
                              "guid": "01965b0f-5564-7b4f-acfe-cd77847b4508"
                            },
                            "IsHighLevel": false,
                            "IsOpCode": true
                          },
                          {
                            "Entity": {},
                            "Children": null,
                            "Tokens": [
                              {
                                "Source": "break",
                                "Line": 17,
                                "StartColumn": 12,
                                "EndColumn": 17,
                                "Scopes": [
                                  "source.ubytec",
                                  "keyword.control.flow.ubytec"
                                ],
                                "Metadata": {
                                  "guid": "01965b0f-5547-7281-91e6-1ef9327a25db"
                                }
                              }
                            ],
                            "Metadata": {
                              "guid": "01965b0f-5564-7435-8b88-b4e4bfda505a"
                            },
                            "IsHighLevel": false,
                            "IsOpCode": true
                          }
                        ],
                        "Tokens": [
                          {
                            "Source": "branch",
                            "Line": 15,
                            "StartColumn": 12,
                            "EndColumn": 18,
                            "Scopes": [
                              "source.ubytec",
                              "keyword.control.flow.ubytec"
                            ],
                            "Metadata": {
                              "guid": "01965b0f-5547-7af4-afb5-ba95eb6f73f0"
                            }
                          },
                          {
                            "Source": "666",
                            "Line": 15,
                            "StartColumn": 19,
                            "EndColumn": 22,
                            "Scopes": [
                              "source.ubytec",
                              "constant.numeric.int.ubytec"
                            ],
                            "Metadata": {
                              "guid": "01965b0f-5547-73eb-b661-1a563e1a3ecf"
                            }
                          }
                        ],
                        "Metadata": {
                          "guid": "01965b0f-5564-7915-b0da-026887641e73",
                          "depth": "      ",
                          "initialDepth": "      "
                        },
                        "IsHighLevel": false,
                        "IsOpCode": true
                      }
                    ],
                    "Sentences": [],
                    "Metadata": {
                      "guid": "01965b0f-5564-737e-a857-2977d2c65fd8",
                      "type": "branch"
                    }
                  }
                ],
                "Metadata": {
                  "guid": "01965b0f-5563-72a0-91b4-c24f12f2b981",
                  "type": "switch"
                }
              }
            ],
            "Metadata": {
              "guid": "01965b0f-5563-70c0-88cd-e943ae8ebd45",
              "type": "while"
            }
          }
        ],
        "Metadata": {
          "guid": "01965b0f-5563-7dcf-bd1a-cbcc50b3486c",
          "type": "block"
        }
      }
    ],
    "Metadata": {
      "guid": "01965b0f-555f-7b19-a03f-b7f924a7ba57",
      "type": "root"
    }
  },
  "Metadata": {
    "guid": "01965b0f-555f-7e14-b0dc-cfb900c4494d",
    "encoding": "Unicode (UTF-8)",
    "langver": "1.0.9243.2223"
  }
}